odoo/addons/product_weight_logistics_uom/README.rst
odoo/addons/product_weight_logistics_uom/__init__.py
odoo/addons/product_weight_logistics_uom/__manifest__.py
odoo/addons/product_weight_logistics_uom/i18n/es.po
odoo/addons/product_weight_logistics_uom/i18n/it.po
odoo/addons/product_weight_logistics_uom/i18n/product_weight_logistics_uom.pot
odoo/addons/product_weight_logistics_uom/readme/CONFIGURE.rst
odoo/addons/product_weight_logistics_uom/readme/CONTRIBUTORS.rst
odoo/addons/product_weight_logistics_uom/readme/CREDITS.rst
odoo/addons/product_weight_logistics_uom/readme/DESCRIPTION.rst
odoo/addons/product_weight_logistics_uom/static/description/icon.png
odoo/addons/product_weight_logistics_uom/static/description/index.html
odoo/addons/product_weight_logistics_uom/tests/__init__.py
odoo/addons/product_weight_logistics_uom/tests/test_product_weight_logistics_uom.py
odoo/addons/product_weight_logistics_uom/wizard/__init__.py
odoo/addons/product_weight_logistics_uom/wizard/product_weight_update.py
odoo14_addon_product_weight_logistics_uom-14.0.1.0.1.dev8.dist-info/METADATA
odoo14_addon_product_weight_logistics_uom-14.0.1.0.1.dev8.dist-info/WHEEL
odoo14_addon_product_weight_logistics_uom-14.0.1.0.1.dev8.dist-info/top_level.txt
odoo14_addon_product_weight_logistics_uom-14.0.1.0.1.dev8.dist-info/RECORD
